excel_to_sql/__init__.py
excel_to_sql/__main__.py
excel_to_sql/__version__.py
excel_to_sql/cli.py
excel_to_sql/auto_pilot/__init__.py
excel_to_sql/auto_pilot/auto_fix.py
excel_to_sql/auto_pilot/detector.py
excel_to_sql/auto_pilot/header_detector.py
excel_to_sql/auto_pilot/recommender.py
excel_to_sql/config/__init__.py
excel_to_sql/entities/__init__.py
excel_to_sql/entities/database.py
excel_to_sql/entities/dataframe.py
excel_to_sql/entities/excel_file.py
excel_to_sql/entities/project.py
excel_to_sql/entities/table.py
excel_to_sql/metadata/__init__.py
excel_to_sql/metadata/models.py
excel_to_sql/metadata/store.py
excel_to_sql/models/__init__.py
excel_to_sql/models/mapping.py
excel_to_sql/profiling/__init__.py
excel_to_sql/profiling/profiler.py
excel_to_sql/profiling/report.py
excel_to_sql/sdk/__init__.py
excel_to_sql/sdk/client.py
excel_to_sql/transformations/__init__.py
excel_to_sql/transformations/calculated.py
excel_to_sql/transformations/hooks.py
excel_to_sql/transformations/mapping.py
excel_to_sql/ui/__init__.py
excel_to_sql/ui/interactive.py
excel_to_sql/validators/__init__.py
excel_to_sql/validators/base.py
excel_to_sql/validators/custom.py
excel_to_sql/validators/reference.py
excel_to_sql/validators/rules.py
excel_to_sql-0.4.1.dist-info/METADATA
excel_to_sql-0.4.1.dist-info/WHEEL
excel_to_sql-0.4.1.dist-info/entry_points.txt
excel_to_sql-0.4.1.dist-info/licenses/LICENSE
excel_to_sql-0.4.1.dist-info/RECORD
