Metadata-Version: 2.4
Name: excel-to-sql
Version: 0.4.1
Summary: CLI tool and Python SDK for importing Excel files to SQLite with advanced transformations and validation
Project-URL: Homepage, https://github.com/wareflowx/excel-to-sql
Project-URL: Repository, https://github.com/wareflowx/excel-to-sql
Project-URL: Documentation, https://github.com/wareflowx/excel-to-sql/blob/main/README.md
Project-URL: Issues, https://github.com/wareflowx/excel-to-sql/issues
Project-URL: Changelog, https://github.com/wareflowx/excel-to-sql/blob/main/CHANGELOG.md
Author-email: Code with dave <davidddpereiraaa6@gmail.com>
License: MIT
License-File: LICENSE
Keywords: cli,data-quality,data-validation,etl,excel,export,import,sql,sqlite,transformations
Classifier: Development Status :: 4 - Beta
Classifier: Intended Audience :: Developers
Classifier: License :: OSI Approved :: MIT License
Classifier: Operating System :: OS Independent
Classifier: Programming Language :: Python :: 3
Classifier: Programming Language :: Python :: 3.10
Classifier: Programming Language :: Python :: 3.11
Classifier: Programming Language :: Python :: 3.12
Classifier: Programming Language :: Python :: 3.13
Classifier: Programming Language :: Python :: 3.14
Classifier: Topic :: Database
Classifier: Topic :: Software Development :: Libraries :: Python Modules
Requires-Python: >=3.10
Requires-Dist: openpyxl>=3.0.0
Requires-Dist: pandas>=2.0.0
Requires-Dist: pydantic>=2.0.0
Requires-Dist: rich>=13.0.0
Requires-Dist: sqlalchemy>=2.0.0
Requires-Dist: typer>=0.12.0
Provides-Extra: dev
Requires-Dist: pytest-cov>=7.0.0; extra == 'dev'
Requires-Dist: pytest>=9.0.2; extra == 'dev'
